[{"title":"Socket Gem","name":"|lime|Transmute","strippedName":"Transmute","imageId":"socketGemImg","description":["|pink|Nothing at all?!"],"passives":[],"flavorText":[],"groupNames":["Nothing?","Upgrade"],"rarity":"Epic","specialFlag":"event","enchantable":false,"gemSlots":0,"extendSlots":0,"level":-1,"dropBase":-1,"dropRange":-1},{"title":"Socket Gem","name":"|lime|Prismatic Luck","strippedName":"Prismatic Luck","imageId":"socketGemImg","description":["|none|丗 Prismatic Aura","|yellow|Adds |white|Luck I"],"passives":[],"flavorText":[],"groupNames":["Any Armor","Upgrade"],"rarity":"Rare","enchantable":false,"gemSlots":0,"extendSlots":0,"level":-1,"dropBase":-1,"dropRange":-1},{"title":"Socket Gem","name":"|lime|Healing Hit","strippedName":"Healing Hit","imageId":"socketGemImg","description":["|orange|+2 Life On Hit"],"passives":[],"flavorText":[],"groupNames":["Offhand Items","Upgrade"],"rarity":"Rare","enchantable":false,"gemSlots":0,"extendSlots":0,"level":-1,"dropBase":-1,"dropRange":-1},{"title":"Socket Gem","name":"|lime|Sky Walker","strippedName":"Sky Walker","imageId":"socketGemImg","description":["|none|丝","|yellow|Gain |white|Slow Falling I |cyan|1|none|峔"],"passives":[],"flavorText":[],"groupNames":["Any Boots","Upgrade"],"rarity":"Epic","specialFlag":"transmute","enchantable":false,"gemSlots":0,"extendSlots":0,"level":-1,"dropBase":-1,"dropRange":-1},{"title":"Socket Gem","name":"|lime|Rousing Text","strippedName":"Rousing Text","imageId":"socketGemImg","description":["|orange|+2 Energy Regeneration"],"passives":[],"flavorText":[],"groupNames":["Spellbooks","Upgrade"],"rarity":"Rare","specialFlag":"transmute","enchantable":false,"gemSlots":0,"extendSlots":0,"level":-1,"dropBase":-1,"dropRange":-1},{"title":"Socket Gem","name":"|lime|Touch Of Dirt","strippedName":"Touch Of Dirt","imageId":"socketGemImg","description":["|orange|+5% Earth Damage"],"passives":[],"flavorText":[],"groupNames":["Offhand Items","Upgrade"],"rarity":"Rare","enchantable":false,"gemSlots":0,"extendSlots":0,"level":-1,"dropBase":-1,"dropRange":-1},{"title":"Socket Gem","name":"|lime|Burn I","strippedName":"Burn I","imageId":"socketGemImg","description":["|orange|+2 Fire Damage"],"passives":[],"flavorText":[],"groupNames":["Any Weapon","Upgrade"],"rarity":"Common","enchantable":false,"gemSlots":0,"extendSlots":0,"level":-1,"dropBase":-1,"dropRange":-1},{"title":"Socket Gem","name":"|lime|Impact IV","strippedName":"Impact IV","imageId":"socketGemImg","description":["|orange|+5 Physical Damage"],"passives":[],"flavorText":[],"groupNames":["Any Weapon","Upgrade"],"rarity":"Epic","enchantable":false,"gemSlots":0,"extendSlots":0,"level":-1,"dropBase":-1,"dropRange":-1},{"title":"Socket Gem","name":"|lime|Elemental Enhancement","strippedName":"Elemental Enhancement","imageId":"socketGemImg","description":["|orange|+3% Damage With Elements"],"passives":[],"flavorText":[],"groupNames":["Offhand Items","Upgrade"],"rarity":"Rare","enchantable":false,"gemSlots":0,"extendSlots":0,"level":-1,"dropBase":-1,"dropRange":-1},{"title":"Socket Gem","name":"|lime|Fletching","strippedName":"Fletching","imageId":"socketGemImg","description":["|orange|+3 Accuracy"],"passives":[],"flavorText":[],"groupNames":["Quivers","Upgrade"],"rarity":"Rare","enchantable":false,"gemSlots":0,"extendSlots":0,"level":-1,"dropBase":-1,"dropRange":-1},{"title":"Socket Gem","name":"|lime|Touch Of Malice","strippedName":"Touch Of Malice","imageId":"socketGemImg","description":["|orange|+5% Shadow Damage"],"passives":[],"flavorText":[],"groupNames":["Offhand Items","Upgrade"],"rarity":"Rare","enchantable":false,"gemSlots":0,"extendSlots":0,"level":-1,"dropBase":-1,"dropRange":-1},{"title":"Socket Gem","name":"|lime|Sunder I","strippedName":"Sunder I","imageId":"socketGemImg","description":["|orange|+6 Armor Penetration"],"passives":[],"flavorText":[],"groupNames":["Physical Weapons","Upgrade"],"rarity":"Common","enchantable":false,"gemSlots":0,"extendSlots":0,"level":-1,"dropBase":-1,"dropRange":-1},{"title":"Socket Gem","name":"|lime|Brilliance","strippedName":"Brilliance","imageId":"socketGemImg","description":["|orange|+1% Skill XP"],"passives":[],"flavorText":[],"groupNames":["Any Armor","Upgrade"],"rarity":"Epic","enchantable":false,"gemSlots":0,"extendSlots":0,"level":-1,"dropBase":-1,"dropRange":-1},{"title":"Socket Gem","name":"|lime|Lifesteal I","strippedName":"Lifesteal I","imageId":"socketGemImg","description":["|orange|+2% Life Steal"],"passives":[],"flavorText":[],"groupNames":["Any Weapon","Upgrade"],"rarity":"Common","enchantable":false,"gemSlots":0,"extendSlots":0,"level":-1,"dropBase":-1,"dropRange":-1},{"title":"Socket Gem","name":"|lime|Parry I","strippedName":"Parry I","imageId":"socketGemImg","description":["|orange|+3 Block"],"passives":[],"flavorText":[],"groupNames":["Melee Weapons","Upgrade"],"rarity":"Common","enchantable":false,"gemSlots":0,"extendSlots":0,"level":-1,"dropBase":-1,"dropRange":-1},{"title":"Socket Gem","name":"|lime|Agile Archery","strippedName":"Agile Archery","imageId":"socketGemImg","description":["|orange|+2 Movement Speed"],"passives":[],"flavorText":[],"groupNames":["Any Bow","Upgrade"],"rarity":"Epic","specialFlag":"transmute","enchantable":false,"gemSlots":0,"extendSlots":0,"level":-1,"dropBase":-1,"dropRange":-1},{"title":"Socket Gem","name":"|lime|True Strike","strippedName":"True Strike","imageId":"socketGemImg","description":["|none|丘","|yellow|Deal |white|8 True Damage"],"passives":[],"flavorText":[],"groupNames":["Any Weapon","Upgrade"],"rarity":"Epic","enchantable":false,"gemSlots":0,"extendSlots":0,"level":-1,"dropBase":-1,"dropRange":-1},{"title":"Socket Gem","name":"|lime|Evade III","strippedName":"Evade III","imageId":"socketGemImg","description":["|orange|+4 Evasion"],"passives":[],"flavorText":[],"groupNames":["Any Armor","Upgrade"],"rarity":"Rare","enchantable":false,"gemSlots":0,"extendSlots":0,"level":-1,"dropBase":-1,"dropRange":-1},{"title":"Socket Gem","name":"|lime|Good Health","strippedName":"Good Health","imageId":"socketGemImg","description":["|orange|+12% Poison Resistance"],"passives":[],"flavorText":[],"groupNames":["Any Armor","Upgrade"],"rarity":"Rare","enchantable":false,"gemSlots":0,"extendSlots":0,"level":-1,"dropBase":-1,"dropRange":-1},{"title":"Socket Gem","name":"|lime|Smash I","strippedName":"Smash I","imageId":"socketGemImg","description":["|orange|+2 Earth Damage"],"passives":[],"flavorText":[],"groupNames":["Any Weapon","Upgrade"],"rarity":"Common","enchantable":false,"gemSlots":0,"extendSlots":0,"level":-1,"dropBase":-1,"dropRange":-1},{"title":"Socket Gem","name":"|lime|Heart of Gold","strippedName":"Heart of Gold","imageId":"socketGemImg","description":["|orange|+10% Bits Dropped"],"passives":[],"flavorText":[],"groupNames":["Any Chest Armor","Upgrade"],"rarity":"Epic","enchantable":false,"gemSlots":0,"extendSlots":0,"level":-1,"dropBase":-1,"dropRange":-1},{"title":"Socket Gem","name":"|lime|Energy III","strippedName":"Energy III","imageId":"socketGemImg","description":["|orange|+14 Maximum Energy"],"passives":[],"flavorText":[],"groupNames":["Any Armor","Upgrade"],"rarity":"Rare","enchantable":false,"gemSlots":0,"extendSlots":0,"level":-1,"dropBase":-1,"dropRange":-1},{"title":"Socket Gem","name":"|lime|Lifesteal IV","strippedName":"Lifesteal IV","imageId":"socketGemImg","description":["|orange|+5% Life Steal"],"passives":[],"flavorText":[],"groupNames":["Any Weapon","Upgrade"],"rarity":"Epic","enchantable":false,"gemSlots":0,"extendSlots":0,"level":-1,"dropBase":-1,"dropRange":-1},{"title":"Socket Gem","name":"|lime|Smash IV","strippedName":"Smash IV","imageId":"socketGemImg","description":["|orange|+5 Earth Damage"],"passives":[],"flavorText":[],"groupNames":["Any Weapon","Upgrade"],"rarity":"Epic","enchantable":false,"gemSlots":0,"extendSlots":0,"level":-1,"dropBase":-1,"dropRange":-1},{"title":"Socket Gem","name":"|lime|Shine I","strippedName":"Shine I","imageId":"socketGemImg","description":["|orange|+2 Light Damage"],"passives":[],"flavorText":[],"groupNames":["Any Weapon","Upgrade"],"rarity":"Common","enchantable":false,"gemSlots":0,"extendSlots":0,"level":-1,"dropBase":-1,"dropRange":-1},{"title":"Socket Gem","name":"|lime|Evade I","strippedName":"Evade I","imageId":"socketGemImg","description":["|orange|+2 Evasion"],"passives":[],"flavorText":[],"groupNames":["Any Armor","Upgrade"],"rarity":"Common","enchantable":false,"gemSlots":0,"extendSlots":0,"level":-1,"dropBase":-1,"dropRange":-1},{"title":"Socket Gem","name":"|lime|First Blood","strippedName":"First Blood","imageId":"socketGemImg","description":["|none|丐","|yellow|Apply |crimson|10儉 |yellow|the first","|yellow|time you wound an enemy"],"passives":[],"flavorText":[],"groupNames":["Any Weapon","Upgrade"],"rarity":"Rare","enchantable":false,"gemSlots":0,"extendSlots":0,"level":-1,"dropBase":-1,"dropRange":-1},{"title":"Socket Gem","name":"|lime|Impact III","strippedName":"Impact III","imageId":"socketGemImg","description":["|orange|+4 Physical Damage"],"passives":[],"flavorText":[],"groupNames":["Any Weapon","Upgrade"],"rarity":"Rare","enchantable":false,"gemSlots":0,"extendSlots":0,"level":-1,"dropBase":-1,"dropRange":-1},{"title":"Socket Gem","name":"|lime|Lifesteal II","strippedName":"Lifesteal II","imageId":"socketGemImg","description":["|orange|+3% Life Steal"],"passives":[],"flavorText":[],"groupNames":["Any Weapon","Upgrade"],"rarity":"Common","enchantable":false,"gemSlots":0,"extendSlots":0,"level":-1,"dropBase":-1,"dropRange":-1},{"title":"Socket Gem","name":"|lime|Opportunist","strippedName":"Opportunist","imageId":"socketGemImg","description":["|none|丙","|yellow|Gain |white|Luck I |cyan|10|none|峔"],"passives":[],"flavorText":[],"groupNames":["Any Weapon","Upgrade"],"rarity":"Rare","enchantable":false,"gemSlots":0,"extendSlots":0,"level":-1,"dropBase":-1,"dropRange":-1},{"title":"Socket Gem","name":"|lime|Smash II","strippedName":"Smash II","imageId":"socketGemImg","description":["|orange|+3 Earth Damage"],"passives":[],"flavorText":[],"groupNames":["Any Weapon","Upgrade"],"rarity":"Common","enchantable":false,"gemSlots":0,"extendSlots":0,"level":-1,"dropBase":-1,"dropRange":-1},{"title":"Socket Gem","name":"|lime|Divine Strike","strippedName":"Divine Strike","imageId":"socketGemImg","description":["|none|丐","|yellow|Deal |white|12 |yellow|bonus |white|Light Damage","|white|[8s Cooldown]"],"passives":[],"flavorText":[],"groupNames":["Any Weapon","Upgrade"],"rarity":"Rare","enchantable":false,"gemSlots":0,"extendSlots":0,"level":-1,"dropBase":-1,"dropRange":-1},{"title":"Socket Gem","name":"|lime|Retard","strippedName":"Retard","imageId":"socketGemImg","description":["|none|丑","|yellow|Inflict |white|Slow II |cyan|2|none|峔"],"passives":[],"flavorText":[],"groupNames":["Heavy Armor","Upgrade"],"rarity":"Rare","enchantable":false,"gemSlots":0,"extendSlots":0,"level":-1,"dropBase":-1,"dropRange":-1},{"title":"Socket Gem","name":"|lime|Blooddrinker","strippedName":"Blooddrinker","imageId":"socketGemImg","description":["|orange|+12 Life On Kill"],"passives":[],"flavorText":[],"groupNames":["Any Weapon","Upgrade"],"rarity":"Epic","enchantable":false,"gemSlots":0,"extendSlots":0,"level":-1,"dropBase":-1,"dropRange":-1},{"title":"Socket Gem","name":"|lime|Shine III","strippedName":"Shine III","imageId":"socketGemImg","description":["|orange|+4 Light Damage"],"passives":[],"flavorText":[],"groupNames":["Any Weapon","Upgrade"],"rarity":"Rare","enchantable":false,"gemSlots":0,"extendSlots":0,"level":-1,"dropBase":-1,"dropRange":-1},{"title":"Socket Gem","name":"|lime|Impact II","strippedName":"Impact II","imageId":"socketGemImg","description":["|orange|+3 Physical Damage"],"passives":[],"flavorText":[],"groupNames":["Any Weapon","Upgrade"],"rarity":"Common","enchantable":false,"gemSlots":0,"extendSlots":0,"level":-1,"dropBase":-1,"dropRange":-1},{"title":"Socket Gem","name":"|lime|Poison","strippedName":"Poison","imageId":"socketGemImg","description":["|orange|+4% Poison Chance"],"passives":[],"flavorText":[],"groupNames":["Any Armor","Upgrade"],"rarity":"Rare","enchantable":false,"gemSlots":0,"extendSlots":0,"level":-1,"dropBase":-1,"dropRange":-1},{"title":"Socket Gem","name":"|lime|Strong Footing","strippedName":"Strong Footing","imageId":"socketGemImg","description":["|orange|+5% Block Recovery"],"passives":[],"flavorText":[],"groupNames":["Any Boots","Upgrade"],"rarity":"Common","enchantable":false,"gemSlots":0,"extendSlots":0,"level":-1,"dropBase":-1,"dropRange":-1},{"title":"Socket Gem","name":"|lime|Eager Elements","strippedName":"Eager Elements","imageId":"socketGemImg","description":["|orange|+5% Element Status Chance"],"passives":[],"flavorText":[],"groupNames":["Offhand Items","Upgrade"],"rarity":"Rare","enchantable":false,"gemSlots":0,"extendSlots":0,"level":-1,"dropBase":-1,"dropRange":-1},{"title":"Socket Gem","name":"|lime|Barrier I","strippedName":"Barrier I","imageId":"socketGemImg","description":["|orange|+2 Maximum Barrier"],"passives":[],"flavorText":[],"groupNames":["Any Armor","Upgrade"],"rarity":"Common","enchantable":false,"gemSlots":0,"extendSlots":0,"level":-1,"dropBase":-1,"dropRange":-1},{"title":"Socket Gem","name":"|lime|Adorn","strippedName":"Adorn","imageId":"socketGemImg","description":["|orange|+2% Bits Dropped"],"passives":[],"flavorText":[],"groupNames":["Any Armor","Upgrade"],"rarity":"Rare","enchantable":false,"gemSlots":0,"extendSlots":0,"level":-1,"dropBase":-1,"dropRange":-1},{"title":"Socket Gem","name":"|lime|Block II","strippedName":"Block II","imageId":"socketGemImg","description":["|orange|+8 Block"],"passives":[],"flavorText":[],"groupNames":["Any Shield","Upgrade"],"rarity":"Common","enchantable":false,"gemSlots":0,"extendSlots":0,"level":-1,"dropBase":-1,"dropRange":-1},{"title":"Socket Gem","name":"|lime|Chill I","strippedName":"Chill I","imageId":"socketGemImg","description":["|orange|+2 Ice Damage"],"passives":[],"flavorText":[],"groupNames":["Any Weapon","Upgrade"],"rarity":"Common","enchantable":false,"gemSlots":0,"extendSlots":0,"level":-1,"dropBase":-1,"dropRange":-1},{"title":"Socket Gem","name":"|lime|Prismatic Regen","strippedName":"Prismatic Regen","imageId":"socketGemImg","description":["|none|丗 Prismatic Aura","|yellow|Adds |white|Regeneration II"],"passives":[],"flavorText":[],"groupNames":["Any Armor","Upgrade"],"rarity":"Epic","enchantable":false,"gemSlots":0,"extendSlots":0,"level":-1,"dropBase":-1,"dropRange":-1},{"title":"Socket Gem","name":"|lime|Soul Siphon","strippedName":"Soul Siphon","imageId":"socketGemImg","description":["|none|丙","|yellow|Start |white|Barrier |yellow|recharge"],"passives":[],"flavorText":[],"groupNames":["Melee Weapons","Upgrade"],"rarity":"Epic","specialFlag":"transmute","enchantable":false,"gemSlots":0,"extendSlots":0,"level":-1,"dropBase":-1,"dropRange":-1},{"title":"Socket Gem","name":"|lime|Respite III","strippedName":"Respite III","imageId":"socketGemImg","description":["|orange|+3 Life Regeneration"],"passives":[],"flavorText":[],"groupNames":["Any Armor","Upgrade"],"rarity":"Rare","enchantable":false,"gemSlots":0,"extendSlots":0,"level":-1,"dropBase":-1,"dropRange":-1},{"title":"Socket Gem","name":"|lime|Coup De Grâce","strippedName":"Coup De Grâce","imageId":"socketGemImg","description":["|none|丘","|yellow|Execute enemies under |white|15% |yellow|Life"],"passives":[],"flavorText":[],"groupNames":["Any Weapon","Upgrade"],"rarity":"Epic","specialFlag":"transmute","enchantable":false,"gemSlots":0,"extendSlots":0,"level":-1,"dropBase":-1,"dropRange":-1},{"title":"Socket Gem","name":"|lime|Precise I","strippedName":"Precise I","imageId":"socketGemImg","description":["|orange|+4 Accuracy"],"passives":[],"flavorText":[],"groupNames":["Any Weapon","Upgrade"],"rarity":"Common","enchantable":false,"gemSlots":0,"extendSlots":0,"level":-1,"dropBase":-1,"dropRange":-1},{"title":"Socket Gem","name":"|lime|Block IV","strippedName":"Block IV","imageId":"socketGemImg","description":["|orange|+12 Block"],"passives":[],"flavorText":[],"groupNames":["Any Shield","Upgrade"],"rarity":"Epic","enchantable":false,"gemSlots":0,"extendSlots":0,"level":-1,"dropBase":-1,"dropRange":-1},{"title":"Socket Gem","name":"|lime|Deflecting Magic","strippedName":"Deflecting Magic","imageId":"socketGemImg","description":["|orange|+2 Maximum Barrier","|orange|+2 Reflected Damage"],"passives":[],"flavorText":[],"groupNames":["Any Shield","Upgrade"],"rarity":"Epic","enchantable":false,"gemSlots":0,"extendSlots":0,"level":-1,"dropBase":-1,"dropRange":-1},{"title":"Socket Gem","name":"|lime|Lumberjack","strippedName":"Lumberjack","imageId":"socketGemImg","description":["|orange|+10% Gathering Speed"],"passives":[],"flavorText":[],"groupNames":["Lumber Axes","Upgrade"],"rarity":"Rare","enchantable":false,"gemSlots":0,"extendSlots":0,"level":-1,"dropBase":-1,"dropRange":-1},{"title":"Socket Gem","name":"|lime|Runic Energy","strippedName":"Runic Energy","imageId":"socketGemImg","description":["|none|丑 [8% Chance]","|yellow|Gain |white|1 |green|Earth Rune"],"passives":[],"flavorText":[],"groupNames":["Any Armor","Upgrade"],"rarity":"Rare","enchantable":false,"gemSlots":0,"extendSlots":0,"level":-1,"dropBase":-1,"dropRange":-1},{"title":"Socket Gem","name":"|lime|Second Chance","strippedName":"Second Chance","imageId":"socketGemImg","description":["|none|丑","|red|[REQ: Less Than 25% Life]","|yellow|Heal |lgreen|25 |yellow|Life","|white|[10s Cooldown]"],"passives":[],"flavorText":[],"groupNames":["Any Armor","Upgrade"],"rarity":"Common","enchantable":false,"gemSlots":0,"extendSlots":0,"level":-1,"dropBase":-1,"dropRange":-1},{"title":"Socket Gem","name":"|lime|Fleet","strippedName":"Fleet","imageId":"socketGemImg","description":["|none|丑","|yellow|Gain |white|Speed I |cyan|5|none|峔"],"passives":[],"flavorText":[],"groupNames":["Any Armor","Upgrade"],"rarity":"Rare","enchantable":false,"gemSlots":0,"extendSlots":0,"level":-1,"dropBase":-1,"dropRange":-1},{"title":"Socket Gem","name":"|lime|Damnation","strippedName":"Damnation","imageId":"socketGemImg","description":["|yellow|Players slain must pass through","|yellow|the |dgray|Door|yellow|..."],"passives":[],"flavorText":[],"groupNames":["Any Weapon","Upgrade"],"rarity":"Epic","specialFlag":"transmute","enchantable":false,"gemSlots":0,"extendSlots":0,"level":-1,"dropBase":-1,"dropRange":-1},{"title":"Socket Gem","name":"|lime|Sustain II","strippedName":"Sustain II","imageId":"socketGemImg","description":["|orange|+2 Energy Regeneration"],"passives":[],"flavorText":[],"groupNames":["Any Armor","Upgrade"],"rarity":"Common","enchantable":false,"gemSlots":0,"extendSlots":0,"level":-1,"dropBase":-1,"dropRange":-1},{"title":"Socket Gem","name":"|lime|Muscle Memory","strippedName":"Muscle Memory","imageId":"socketGemImg","description":["|orange|+4% Combat XP"],"passives":[],"flavorText":[],"groupNames":["Any Helmet","Upgrade"],"rarity":"Epic","specialFlag":"event","enchantable":false,"gemSlots":0,"extendSlots":0,"level":-1,"dropBase":-1,"dropRange":-1},{"title":"Socket Gem","name":"|lime|Reinforcement II","strippedName":"Reinforcement II","imageId":"socketGemImg","description":["|orange|+3 Armor"],"passives":[],"flavorText":[],"groupNames":["Any Armor","Upgrade"],"rarity":"Common","enchantable":false,"gemSlots":0,"extendSlots":0,"level":-1,"dropBase":-1,"dropRange":-1},{"title":"Socket Gem","name":"|lime|Gem Resonance","strippedName":"Gem Resonance","imageId":"socketGemImg","description":["|orange|+10% Mining Gems"],"passives":[],"flavorText":[],"groupNames":["Pickaxes","Upgrade"],"rarity":"Epic","enchantable":false,"gemSlots":0,"extendSlots":0,"level":-1,"dropBase":-1,"dropRange":-1},{"title":"Socket Gem","name":"|lime|Gaudy Lure","strippedName":"Gaudy Lure","imageId":"socketGemImg","description":["|orange|+5% Fishing Treasures"],"passives":[],"flavorText":[],"groupNames":["Fishing Rods","Upgrade"],"rarity":"Rare","enchantable":false,"gemSlots":0,"extendSlots":0,"level":-1,"dropBase":-1,"dropRange":-1},{"title":"Socket Gem","name":"|lime|Block III","strippedName":"Block III","imageId":"socketGemImg","description":["|orange|+10 Block"],"passives":[],"flavorText":[],"groupNames":["Any Shield","Upgrade"],"rarity":"Rare","enchantable":false,"gemSlots":0,"extendSlots":0,"level":-1,"dropBase":-1,"dropRange":-1},{"title":"Socket Gem","name":"|lime|Pretty Angry","strippedName":"Pretty Angry","imageId":"socketGemImg","description":["|orange|+2% Rage On Hit"],"passives":[],"flavorText":[],"groupNames":["Any Weapon","Upgrade"],"rarity":"Rare","enchantable":false,"gemSlots":0,"extendSlots":0,"level":-1,"dropBase":-1,"dropRange":-1},{"title":"Socket Gem","name":"|lime|Respite IV","strippedName":"Respite IV","imageId":"socketGemImg","description":["|orange|+4 Life Regeneration"],"passives":[],"flavorText":[],"groupNames":["Any Armor","Upgrade"],"rarity":"Epic","enchantable":false,"gemSlots":0,"extendSlots":0,"level":-1,"dropBase":-1,"dropRange":-1},{"title":"Socket Gem","name":"|lime|Shade II","strippedName":"Shade II","imageId":"socketGemImg","description":["|orange|+3 Shadow Damage"],"passives":[],"flavorText":[],"groupNames":["Any Weapon","Upgrade"],"rarity":"Common","enchantable":false,"gemSlots":0,"extendSlots":0,"level":-1,"dropBase":-1,"dropRange":-1},{"title":"Socket Gem","name":"|lime|Smash III","strippedName":"Smash III","imageId":"socketGemImg","description":["|orange|+4 Earth Damage"],"passives":[],"flavorText":[],"groupNames":["Any Weapon","Upgrade"],"rarity":"Rare","enchantable":false,"gemSlots":0,"extendSlots":0,"level":-1,"dropBase":-1,"dropRange":-1},{"title":"Socket Gem","name":"|lime|Reinforcement IV","strippedName":"Reinforcement IV","imageId":"socketGemImg","description":["|orange|+5 Armor"],"passives":[],"flavorText":[],"groupNames":["Any Armor","Upgrade"],"rarity":"Epic","enchantable":false,"gemSlots":0,"extendSlots":0,"level":-1,"dropBase":-1,"dropRange":-1},{"title":"Socket Gem","name":"|lime|Glimmer","strippedName":"Glimmer","imageId":"socketGemImg","description":["|orange|+3% Loot Bonus"],"passives":[],"flavorText":[],"groupNames":["Offhand Items","Upgrade"],"rarity":"Epic","enchantable":false,"gemSlots":0,"extendSlots":0,"level":-1,"dropBase":-1,"dropRange":-1},{"title":"Socket Gem","name":"|lime|Sustain III","strippedName":"Sustain III","imageId":"socketGemImg","description":["|orange|+3 Energy Regeneration"],"passives":[],"flavorText":[],"groupNames":["Any Armor","Upgrade"],"rarity":"Rare","enchantable":false,"gemSlots":0,"extendSlots":0,"level":-1,"dropBase":-1,"dropRange":-1},{"title":"Socket Gem","name":"|lime|Shade IV","strippedName":"Shade IV","imageId":"socketGemImg","description":["|orange|+5 Shadow Damage"],"passives":[],"flavorText":[],"groupNames":["Any Weapon","Upgrade"],"rarity":"Epic","enchantable":false,"gemSlots":0,"extendSlots":0,"level":-1,"dropBase":-1,"dropRange":-1},{"title":"Socket Gem","name":"|lime|Sunder IV","strippedName":"Sunder IV","imageId":"socketGemImg","description":["|orange|+12 Armor Penetration"],"passives":[],"flavorText":[],"groupNames":["Physical Weapons","Upgrade"],"rarity":"Epic","enchantable":false,"gemSlots":0,"extendSlots":0,"level":-1,"dropBase":-1,"dropRange":-1},{"title":"Socket Gem","name":"|lime|Prismatic Speed","strippedName":"Prismatic Speed","imageId":"socketGemImg","description":["|none|丗 Prismatic Aura","|yellow|Adds |white|Speed I"],"passives":[],"flavorText":[],"groupNames":["Any Armor","Upgrade"],"rarity":"Rare","enchantable":false,"gemSlots":0,"extendSlots":0,"level":-1,"dropBase":-1,"dropRange":-1},{"title":"Socket Gem","name":"|lime|Spirit Wind","strippedName":"Spirit Wind","imageId":"socketGemImg","description":["|none|丛","|yellow|Restore |white|10% |yellow|barrier","|white|[4s Cooldown]"],"passives":[],"flavorText":[],"groupNames":["Any Armor","Upgrade"],"rarity":"Rare","enchantable":false,"gemSlots":0,"extendSlots":0,"level":-1,"dropBase":-1,"dropRange":-1},{"title":"Socket Gem","name":"|lime|Lifesteal III","strippedName":"Lifesteal III","imageId":"socketGemImg","description":["|orange|+4% Life Steal"],"passives":[],"flavorText":[],"groupNames":["Any Weapon","Upgrade"],"rarity":"Rare","enchantable":false,"gemSlots":0,"extendSlots":0,"level":-1,"dropBase":-1,"dropRange":-1},{"title":"Socket Gem","name":"|lime|Quickening","strippedName":"Quickening","imageId":"socketGemImg","description":["|orange|+2% Cooldown Reduction"],"passives":[],"flavorText":[],"groupNames":["Cloth Armor","Upgrade"],"rarity":"Rare","enchantable":false,"gemSlots":0,"extendSlots":0,"level":-1,"dropBase":-1,"dropRange":-1},{"title":"Socket Gem","name":"|lime|Sunder II","strippedName":"Sunder II","imageId":"socketGemImg","description":["|orange|+8 Armor Penetration"],"passives":[],"flavorText":[],"groupNames":["Physical Weapons","Upgrade"],"rarity":"Common","enchantable":false,"gemSlots":0,"extendSlots":0,"level":-1,"dropBase":-1,"dropRange":-1},{"title":"Socket Gem","name":"|lime|Brutality III","strippedName":"Brutality III","imageId":"socketGemImg","description":["|orange|+14% Critical Multiplier"],"passives":[],"flavorText":[],"groupNames":["Any Weapon","Upgrade"],"rarity":"Rare","enchantable":false,"gemSlots":0,"extendSlots":0,"level":-1,"dropBase":-1,"dropRange":-1},{"title":"Socket Gem","name":"|lime|Precise II","strippedName":"Precise II","imageId":"socketGemImg","description":["|orange|+6 Accuracy"],"passives":[],"flavorText":[],"groupNames":["Any Weapon","Upgrade"],"rarity":"Common","enchantable":false,"gemSlots":0,"extendSlots":0,"level":-1,"dropBase":-1,"dropRange":-1},{"title":"Socket Gem","name":"|lime|Life III","strippedName":"Life III","imageId":"socketGemImg","description":["|orange|+6 Maximum Life"],"passives":[],"flavorText":[],"groupNames":["Any Armor","Upgrade"],"rarity":"Rare","enchantable":false,"gemSlots":0,"extendSlots":0,"level":-1,"dropBase":-1,"dropRange":-1},{"title":"Socket Gem","name":"|lime|Touch Of Cold","strippedName":"Touch Of Cold","imageId":"socketGemImg","description":["|orange|+5% Ice Damage"],"passives":[],"flavorText":[],"groupNames":["Offhand Items","Upgrade"],"rarity":"Rare","enchantable":false,"gemSlots":0,"extendSlots":0,"level":-1,"dropBase":-1,"dropRange":-1},{"title":"Socket Gem","name":"|lime|Prismatic Power","strippedName":"Prismatic Power","imageId":"socketGemImg","description":["|none|丗 Prismatic Aura","|yellow|Adds |white|Power II"],"passives":[],"flavorText":[],"groupNames":["Any Armor","Upgrade"],"rarity":"Epic","enchantable":false,"gemSlots":0,"extendSlots":0,"level":-1,"dropBase":-1,"dropRange":-1},{"title":"Socket Gem","name":"|lime|Resistance III","strippedName":"Resistance III","imageId":"socketGemImg","description":["|orange|+4% Elemental Resist"],"passives":[],"flavorText":[],"groupNames":["Any Armor","Upgrade"],"rarity":"Rare","enchantable":false,"gemSlots":0,"extendSlots":0,"level":-1,"dropBase":-1,"dropRange":-1},{"title":"Socket Gem","name":"|lime|Zap IV","strippedName":"Zap IV","imageId":"socketGemImg","description":["|orange|+5 Lightning Damage"],"passives":[],"flavorText":[],"groupNames":["Any Weapon","Upgrade"],"rarity":"Epic","enchantable":false,"gemSlots":0,"extendSlots":0,"level":-1,"dropBase":-1,"dropRange":-1},{"title":"Socket Gem","name":"|lime|Precise IV","strippedName":"Precise IV","imageId":"socketGemImg","description":["|orange|+10 Accuracy"],"passives":[],"flavorText":[],"groupNames":["Any Weapon","Upgrade"],"rarity":"Epic","enchantable":false,"gemSlots":0,"extendSlots":0,"level":-1,"dropBase":-1,"dropRange":-1},{"title":"Socket Gem","name":"|lime|Luck of PSwag","strippedName":"Luck of PSwag","imageId":"socketGemImg","description":["|orange|+7% Bits Dropped","|orange|+2% Swagger"],"passives":[],"flavorText":[],"groupNames":["Spellbooks","Upgrade"],"rarity":"Epic","enchantable":false,"gemSlots":0,"extendSlots":0,"level":-1,"dropBase":-1,"dropRange":-1},{"title":"Socket Gem","name":"|lime|Reinforcement I","strippedName":"Reinforcement I","imageId":"socketGemImg","description":["|orange|+2 Armor"],"passives":[],"flavorText":[],"groupNames":["Any Armor","Upgrade"],"rarity":"Common","enchantable":false,"gemSlots":0,"extendSlots":0,"level":-1,"dropBase":-1,"dropRange":-1},{"title":"Socket Gem","name":"|lime|Shade I","strippedName":"Shade I","imageId":"socketGemImg","description":["|orange|+2 Shadow Damage"],"passives":[],"flavorText":[],"groupNames":["Any Weapon","Upgrade"],"rarity":"Common","enchantable":false,"gemSlots":0,"extendSlots":0,"level":-1,"dropBase":-1,"dropRange":-1},{"title":"Socket Gem","name":"|lime|Sustain I","strippedName":"Sustain I","imageId":"socketGemImg","description":["|orange|+1 Energy Regeneration"],"passives":[],"flavorText":[],"groupNames":["Any Armor","Upgrade"],"rarity":"Common","enchantable":false,"gemSlots":0,"extendSlots":0,"level":-1,"dropBase":-1,"dropRange":-1},{"title":"Socket Gem","name":"|lime|Chill IV","strippedName":"Chill IV","imageId":"socketGemImg","description":["|orange|+5 Ice Damage"],"passives":[],"flavorText":[],"groupNames":["Any Weapon","Upgrade"],"rarity":"Epic","enchantable":false,"gemSlots":0,"extendSlots":0,"level":-1,"dropBase":-1,"dropRange":-1},{"title":"Socket Gem","name":"|lime|Reinforcement III","strippedName":"Reinforcement III","imageId":"socketGemImg","description":["|orange|+4 Armor"],"passives":[],"flavorText":[],"groupNames":["Any Armor","Upgrade"],"rarity":"Rare","enchantable":false,"gemSlots":0,"extendSlots":0,"level":-1,"dropBase":-1,"dropRange":-1},{"title":"Socket Gem","name":"|lime|Parry II","strippedName":"Parry II","imageId":"socketGemImg","description":["|orange|+4 Block"],"passives":[],"flavorText":[],"groupNames":["Melee Weapons","Upgrade"],"rarity":"Common","enchantable":false,"gemSlots":0,"extendSlots":0,"level":-1,"dropBase":-1,"dropRange":-1},{"title":"Socket Gem","name":"|lime|Page Turner","strippedName":"Page Turner","imageId":"socketGemImg","description":["|orange|+3% Attack Speed"],"passives":[],"flavorText":[],"groupNames":["Spellbooks","Upgrade"],"rarity":"Rare","enchantable":false,"gemSlots":0,"extendSlots":0,"level":-1,"dropBase":-1,"dropRange":-1},{"title":"Socket Gem","name":"|lime|Respite II","strippedName":"Respite II","imageId":"socketGemImg","description":["|orange|+2 Life Regeneration"],"passives":[],"flavorText":[],"groupNames":["Any Armor","Upgrade"],"rarity":"Common","enchantable":false,"gemSlots":0,"extendSlots":0,"level":-1,"dropBase":-1,"dropRange":-1},{"title":"Socket Gem","name":"|lime|Booksmarts","strippedName":"Booksmarts","imageId":"socketGemImg","description":["|orange|+2% Combat XP"],"passives":[],"flavorText":[],"groupNames":["Spellbooks","Upgrade"],"rarity":"Epic","enchantable":false,"gemSlots":0,"extendSlots":0,"level":-1,"dropBase":-1,"dropRange":-1},{"title":"Socket Gem","name":"|lime|Evade II","strippedName":"Evade II","imageId":"socketGemImg","description":["|orange|+3 Evasion"],"passives":[],"flavorText":[],"groupNames":["Any Armor","Upgrade"],"rarity":"Common","enchantable":false,"gemSlots":0,"extendSlots":0,"level":-1,"dropBase":-1,"dropRange":-1},{"title":"Socket Gem","name":"|lime|Parry IV","strippedName":"Parry IV","imageId":"socketGemImg","description":["|orange|+6 Block"],"passives":[],"flavorText":[],"groupNames":["Melee Weapons","Upgrade"],"rarity":"Epic","enchantable":false,"gemSlots":0,"extendSlots":0,"level":-1,"dropBase":-1,"dropRange":-1},{"title":"Socket Gem","name":"|lime|Mighty Charge","strippedName":"Mighty Charge","imageId":"socketGemImg","description":["|orange|+2 Movement Speed"],"passives":[],"flavorText":[],"groupNames":["Any Shield","Upgrade"],"rarity":"Epic","enchantable":false,"gemSlots":0,"extendSlots":0,"level":-1,"dropBase":-1,"dropRange":-1},{"title":"Socket Gem","name":"|lime|Brutality I","strippedName":"Brutality I","imageId":"socketGemImg","description":["|orange|+10% Critical Multiplier"],"passives":[],"flavorText":[],"groupNames":["Any Weapon","Upgrade"],"rarity":"Common","enchantable":false,"gemSlots":0,"extendSlots":0,"level":-1,"dropBase":-1,"dropRange":-1},{"title":"Socket Gem","name":"|lime|Respite I","strippedName":"Respite I","imageId":"socketGemImg","description":["|orange|+1 Life Regeneration"],"passives":[],"flavorText":[],"groupNames":["Any Armor","Upgrade"],"rarity":"Common","enchantable":false,"gemSlots":0,"extendSlots":0,"level":-1,"dropBase":-1,"dropRange":-1},{"title":"Socket Gem","name":"|lime|Apathy","strippedName":"Apathy","imageId":"socketGemImg","description":["|none|且","|yellow|Inflict |white|Slow I |pink|22|none|峑 |cyan|20|none|峔"],"passives":[],"flavorText":[],"groupNames":["Any Armor","Upgrade"],"rarity":"Rare","enchantable":false,"gemSlots":0,"extendSlots":0,"level":-1,"dropBase":-1,"dropRange":-1},{"title":"Socket Gem","name":"|lime|Hawk Eyes","strippedName":"Hawk Eyes","imageId":"socketGemImg","description":["|orange|+2 Physical Damage"],"passives":[],"flavorText":[],"groupNames":["Any Helmet","Upgrade"],"rarity":"Epic","specialFlag":"transmute","enchantable":false,"gemSlots":0,"extendSlots":0,"level":-1,"dropBase":-1,"dropRange":-1},{"title":"Socket Gem","name":"|lime|Sustain IV","strippedName":"Sustain IV","imageId":"socketGemImg","description":["|orange|+4 Energy Regeneration"],"passives":[],"flavorText":[],"groupNames":["Any Armor","Upgrade"],"rarity":"Epic","enchantable":false,"gemSlots":0,"extendSlots":0,"level":-1,"dropBase":-1,"dropRange":-1},{"title":"Socket Gem","name":"|lime|Burn III","strippedName":"Burn III","imageId":"socketGemImg","description":["|orange|+4 Fire Damage"],"passives":[],"flavorText":[],"groupNames":["Any Weapon","Upgrade"],"rarity":"Rare","enchantable":false,"gemSlots":0,"extendSlots":0,"level":-1,"dropBase":-1,"dropRange":-1},{"title":"Socket Gem","name":"|lime|Chill II","strippedName":"Chill II","imageId":"socketGemImg","description":["|orange|+3 Ice Damage"],"passives":[],"flavorText":[],"groupNames":["Any Weapon","Upgrade"],"rarity":"Common","enchantable":false,"gemSlots":0,"extendSlots":0,"level":-1,"dropBase":-1,"dropRange":-1},{"title":"Socket Gem","name":"|lime|Evade IV","strippedName":"Evade IV","imageId":"socketGemImg","description":["|orange|+5 Evasion"],"passives":[],"flavorText":[],"groupNames":["Any Armor","Upgrade"],"rarity":"Epic","enchantable":false,"gemSlots":0,"extendSlots":0,"level":-1,"dropBase":-1,"dropRange":-1},{"title":"Socket Gem","name":"|lime|Lethality I","strippedName":"Lethality I","imageId":"socketGemImg","description":["|orange|+6% Critical Chance"],"passives":[],"flavorText":[],"groupNames":["Any Weapon","Upgrade"],"rarity":"Common","enchantable":false,"gemSlots":0,"extendSlots":0,"level":-1,"dropBase":-1,"dropRange":-1},{"title":"Socket Gem","name":"|lime|Blood Trail","strippedName":"Blood Trail","imageId":"socketGemImg","description":["|orange|+4% Bleed Chance"],"passives":[],"flavorText":[],"groupNames":["Quivers","Upgrade"],"rarity":"Rare","enchantable":false,"gemSlots":0,"extendSlots":0,"level":-1,"dropBase":-1,"dropRange":-1},{"title":"Socket Gem","name":"|lime|Spotter","strippedName":"Spotter","imageId":"socketGemImg","description":["|orange|+4% Minion Max Life"],"passives":[],"flavorText":[],"groupNames":["Any Armor","Upgrade"],"rarity":"Rare","enchantable":false,"gemSlots":0,"extendSlots":0,"level":-1,"dropBase":-1,"dropRange":-1},{"title":"Socket Gem","name":"|lime|Pumpkin Bomb","strippedName":"Pumpkin Bomb","imageId":"socketGemImg","description":["|none|丗 Bomb Toss","|purple|Shadow Damage Multiplier: 1.4x","|lgray|Inflict |purple||ul|10 Corruption"],"passives":[],"flavorText":[],"groupNames":["Any Weapon","Upgrade"],"rarity":"Epic","specialFlag":"event","enchantable":false,"gemSlots":0,"extendSlots":0,"level":-1,"dropBase":-1,"dropRange":-1},{"title":"Socket Gem","name":"|lime|Seeking Eyes","strippedName":"Seeking Eyes","imageId":"socketGemImg","description":["|orange|+8 Accuracy"],"passives":[],"flavorText":[],"groupNames":["Any Helmet","Upgrade"],"rarity":"Rare","enchantable":false,"gemSlots":0,"extendSlots":0,"level":-1,"dropBase":-1,"dropRange":-1},{"title":"Socket Gem","name":"|lime|Final Stand","strippedName":"Final Stand","imageId":"socketGemImg","description":["|orange|+2% Life Regeneration","|orange|+5 Tenacity"],"passives":[],"flavorText":[],"groupNames":["Any Shield","Upgrade"],"rarity":"Epic","enchantable":false,"gemSlots":0,"extendSlots":0,"level":-1,"dropBase":-1,"dropRange":-1},{"title":"Socket Gem","name":"|lime|Tectonic Plate","strippedName":"Tectonic Plate","imageId":"socketGemImg","description":["|orange|+8% Lightning Resistance","|orange|+3% Earth Damage"],"passives":[],"flavorText":[],"groupNames":["Heavy Armor","Upgrade"],"rarity":"Epic","enchantable":false,"gemSlots":0,"extendSlots":0,"level":-1,"dropBase":-1,"dropRange":-1},{"title":"Socket Gem","name":"|lime|Venom","strippedName":"Venom","imageId":"socketGemImg","description":["|orange|+12% Poison Chance"],"passives":[],"flavorText":[],"groupNames":["Any Weapon","Upgrade"],"rarity":"Rare","enchantable":false,"gemSlots":0,"extendSlots":0,"level":-1,"dropBase":-1,"dropRange":-1},{"title":"Socket Gem","name":"|lime|Touch Of Thunder","strippedName":"Touch Of Thunder","imageId":"socketGemImg","description":["|orange|+5% Lightning Damage"],"passives":[],"flavorText":[],"groupNames":["Offhand Items","Upgrade"],"rarity":"Rare","enchantable":false,"gemSlots":0,"extendSlots":0,"level":-1,"dropBase":-1,"dropRange":-1},{"title":"Socket Gem","name":"|lime|Parry III","strippedName":"Parry III","imageId":"socketGemImg","description":["|orange|+5 Block"],"passives":[],"flavorText":[],"groupNames":["Melee Weapons","Upgrade"],"rarity":"Rare","enchantable":false,"gemSlots":0,"extendSlots":0,"level":-1,"dropBase":-1,"dropRange":-1},{"title":"Socket Gem","name":"|lime|Fast Cast","strippedName":"Fast Cast","imageId":"socketGemImg","description":["|orange|+2% Cooldown Reduction"],"passives":[],"flavorText":[],"groupNames":["Offhand Items","Upgrade"],"rarity":"Rare","enchantable":false,"gemSlots":0,"extendSlots":0,"level":-1,"dropBase":-1,"dropRange":-1},{"title":"Socket Gem","name":"|lime|Flow","strippedName":"Flow","imageId":"socketGemImg","description":["|none|且","|yellow|Gain |white|Regen II |cyan|8|none|峔","|yellow|Gain |white|Speed I |cyan|10|none|峔"],"passives":[],"flavorText":[],"groupNames":["Any Armor","Upgrade"],"rarity":"Epic","specialFlag":"transmute","enchantable":false,"gemSlots":0,"extendSlots":0,"level":-1,"dropBase":-1,"dropRange":-1},{"title":"Socket Gem","name":"|lime|Fear","strippedName":"Fear","imageId":"socketGemImg","description":["|none|且","|yellow|Inflict |white|Vulnerable II |pink|22|none|峑 |cyan|20|none|峔"],"passives":[],"flavorText":[],"groupNames":["Any Armor","Upgrade"],"rarity":"Rare","enchantable":false,"gemSlots":0,"extendSlots":0,"level":-1,"dropBase":-1,"dropRange":-1},{"title":"Socket Gem","name":"|lime|Speed Read","strippedName":"Speed Read","imageId":"socketGemImg","description":["|orange|+4% Cooldown Reduction"],"passives":[],"flavorText":[],"groupNames":["Spellbooks","Upgrade"],"rarity":"Rare","specialFlag":"transmute","enchantable":false,"gemSlots":0,"extendSlots":0,"level":-1,"dropBase":-1,"dropRange":-1},{"title":"Socket Gem","name":"|lime|Ether Step","strippedName":"Ether Step","imageId":"socketGemImg","description":["|none|丗 Blink","|yellow|Restore |white|2% + 6 Barrier"],"passives":[],"flavorText":[],"groupNames":["Any Boots","Upgrade"],"rarity":"Epic","specialFlag":"transmute","enchantable":false,"gemSlots":0,"extendSlots":0,"level":-1,"dropBase":-1,"dropRange":-1},{"title":"Socket Gem","name":"|lime|Quick Pick","strippedName":"Quick Pick","imageId":"socketGemImg","description":["|orange|+10% Mining Speed"],"passives":[],"flavorText":[],"groupNames":["Pickaxes","Upgrade"],"rarity":"Rare","enchantable":false,"gemSlots":0,"extendSlots":0,"level":-1,"dropBase":-1,"dropRange":-1},{"title":"Socket Gem","name":"|lime|Fighting Dirty","strippedName":"Fighting Dirty","imageId":"socketGemImg","description":["|none|且","|yellow|Gain |white|2 |green|Earth Runes"],"passives":[],"flavorText":[],"groupNames":["Any Armor","Upgrade"],"rarity":"Epic","enchantable":false,"gemSlots":0,"extendSlots":0,"level":-1,"dropBase":-1,"dropRange":-1},{"title":"Socket Gem","name":"|lime|Sacred Barrier","strippedName":"Sacred Barrier","imageId":"socketGemImg","description":["|orange|+10 Barrier Regeneration"],"passives":[],"flavorText":[],"groupNames":["Any Shield","Upgrade"],"rarity":"Epic","enchantable":false,"gemSlots":0,"extendSlots":0,"level":-1,"dropBase":-1,"dropRange":-1},{"title":"Socket Gem","name":"|lime|Gluttony","strippedName":"Gluttony","imageId":"socketGemImg","description":["|orange|+2% Life Steal","|orange|+2 Life On Hit"],"passives":[],"flavorText":[],"groupNames":["Any Shield","Upgrade"],"rarity":"Epic","enchantable":false,"gemSlots":0,"extendSlots":0,"level":-1,"dropBase":-1,"dropRange":-1},{"title":"Socket Gem","name":"|lime|Insight","strippedName":"Insight","imageId":"socketGemImg","description":["|orange|+4% Combat XP"],"passives":[],"flavorText":[],"groupNames":["Any Helmet","Upgrade"],"rarity":"Epic","specialFlag":"event","enchantable":false,"gemSlots":0,"extendSlots":0,"level":-1,"dropBase":-1,"dropRange":-1},{"title":"Socket Gem","name":"|lime|Lacerate III","strippedName":"Lacerate III","imageId":"socketGemImg","description":["|orange|+8% Bleed Chance"],"passives":[],"flavorText":[],"groupNames":["Physical Weapons","Upgrade"],"rarity":"Rare","enchantable":false,"gemSlots":0,"extendSlots":0,"level":-1,"dropBase":-1,"dropRange":-1},{"title":"Socket Gem","name":"|lime|Glint","strippedName":"Glint","imageId":"socketGemImg","description":["|orange|+5% Loot Rarity"],"passives":[],"flavorText":[],"groupNames":["Offhand Items","Upgrade"],"rarity":"Epic","specialFlag":"transmute","enchantable":false,"gemSlots":0,"extendSlots":0,"level":-1,"dropBase":-1,"dropRange":-1},{"title":"Socket Gem","name":"|lime|Soul Eater","strippedName":"Soul Eater","imageId":"socketGemImg","description":["|orange|+3 Life On Kill"],"passives":[],"flavorText":[],"groupNames":["Offhand Items","Upgrade"],"rarity":"Rare","enchantable":false,"gemSlots":0,"extendSlots":0,"level":-1,"dropBase":-1,"dropRange":-1},{"title":"Socket Gem","name":"|lime|Prismatic Resist","strippedName":"Prismatic Resist","imageId":"socketGemImg","description":["|none|丗 Prismatic Aura","|yellow|Adds |white|Resist II"],"passives":[],"flavorText":[],"groupNames":["Any Armor","Upgrade"],"rarity":"Rare","enchantable":false,"gemSlots":0,"extendSlots":0,"level":-1,"dropBase":-1,"dropRange":-1},{"title":"Socket Gem","name":"|lime|Energy II","strippedName":"Energy II","imageId":"socketGemImg","description":["|orange|+12 Maximum Energy"],"passives":[],"flavorText":[],"groupNames":["Any Armor","Upgrade"],"rarity":"Common","enchantable":false,"gemSlots":0,"extendSlots":0,"level":-1,"dropBase":-1,"dropRange":-1},{"title":"Socket Gem","name":"|lime|Leeching Hit","strippedName":"Leeching Hit","imageId":"socketGemImg","description":["|orange|+1% Life Steal"],"passives":[],"flavorText":[],"groupNames":["Offhand Items","Upgrade"],"rarity":"Rare","enchantable":false,"gemSlots":0,"extendSlots":0,"level":-1,"dropBase":-1,"dropRange":-1},{"title":"Socket Gem","name":"|lime|Zap I","strippedName":"Zap I","imageId":"socketGemImg","description":["|orange|+2 Lightning Damage"],"passives":[],"flavorText":[],"groupNames":["Any Weapon","Upgrade"],"rarity":"Common","enchantable":false,"gemSlots":0,"extendSlots":0,"level":-1,"dropBase":-1,"dropRange":-1},{"title":"Socket Gem","name":"|lime|Deflect","strippedName":"Deflect","imageId":"socketGemImg","description":["|orange|+2 Block"],"passives":[],"flavorText":[],"groupNames":["Any Armor","Upgrade"],"rarity":"Rare","enchantable":false,"gemSlots":0,"extendSlots":0,"level":-1,"dropBase":-1,"dropRange":-1},{"title":"Socket Gem","name":"|lime|Resistance I","strippedName":"Resistance I","imageId":"socketGemImg","description":["|orange|+2% Elemental Resist"],"passives":[],"flavorText":[],"groupNames":["Any Armor","Upgrade"],"rarity":"Common","enchantable":false,"gemSlots":0,"extendSlots":0,"level":-1,"dropBase":-1,"dropRange":-1},{"title":"Socket Gem","name":"|lime|Resistance II","strippedName":"Resistance II","imageId":"socketGemImg","description":["|orange|+3% Elemental Resist"],"passives":[],"flavorText":[],"groupNames":["Any Armor","Upgrade"],"rarity":"Common","enchantable":false,"gemSlots":0,"extendSlots":0,"level":-1,"dropBase":-1,"dropRange":-1},{"title":"Socket Gem","name":"|lime|Subtle Stamina","strippedName":"Subtle Stamina","imageId":"socketGemImg","description":["|orange|+1 Energy Regeneration"],"passives":[],"flavorText":[],"groupNames":["Offhand Items","Upgrade"],"rarity":"Rare","enchantable":false,"gemSlots":0,"extendSlots":0,"level":-1,"dropBase":-1,"dropRange":-1},{"title":"Socket Gem","name":"|lime|Enlightenment","strippedName":"Enlightenment","imageId":"socketGemImg","description":["|orange|+4% Skill XP"],"passives":[],"flavorText":[],"groupNames":["Any Helmet","Upgrade"],"rarity":"Epic","specialFlag":"event","enchantable":false,"gemSlots":0,"extendSlots":0,"level":-1,"dropBase":-1,"dropRange":-1},{"title":"Socket Gem","name":"|lime|Energy IV","strippedName":"Energy IV","imageId":"socketGemImg","description":["|orange|+16 Maximum Energy"],"passives":[],"flavorText":[],"groupNames":["Any Armor","Upgrade"],"rarity":"Epic","enchantable":false,"gemSlots":0,"extendSlots":0,"level":-1,"dropBase":-1,"dropRange":-1},{"title":"Socket Gem","name":"|lime|Life IV","strippedName":"Life IV","imageId":"socketGemImg","description":["|orange|+8 Maximum Life"],"passives":[],"flavorText":[],"groupNames":["Any Armor","Upgrade"],"rarity":"Epic","enchantable":false,"gemSlots":0,"extendSlots":0,"level":-1,"dropBase":-1,"dropRange":-1},{"title":"Socket Gem","name":"|lime|Zap II","strippedName":"Zap II","imageId":"socketGemImg","description":["|orange|+3 Lightning Damage"],"passives":[],"flavorText":[],"groupNames":["Any Weapon","Upgrade"],"rarity":"Common","enchantable":false,"gemSlots":0,"extendSlots":0,"level":-1,"dropBase":-1,"dropRange":-1},{"title":"Socket Gem","name":"|lime|Lacerate IV","strippedName":"Lacerate IV","imageId":"socketGemImg","description":["|orange|+10% Bleed Chance"],"passives":[],"flavorText":[],"groupNames":["Physical Weapons","Upgrade"],"rarity":"Epic","enchantable":false,"gemSlots":0,"extendSlots":0,"level":-1,"dropBase":-1,"dropRange":-1},{"title":"Socket Gem","name":"|lime|Bloodsucker","strippedName":"Bloodsucker","imageId":"socketGemImg","description":["|orange|+8 Life On Kill"],"passives":[],"flavorText":[],"groupNames":["Any Weapon","Upgrade"],"rarity":"Common","enchantable":false,"gemSlots":0,"extendSlots":0,"level":-1,"dropBase":-1,"dropRange":-1},{"title":"Socket Gem","name":"|lime|Lacerate II","strippedName":"Lacerate II","imageId":"socketGemImg","description":["|orange|+7% Bleed Chance"],"passives":[],"flavorText":[],"groupNames":["Physical Weapons","Upgrade"],"rarity":"Common","enchantable":false,"gemSlots":0,"extendSlots":0,"level":-1,"dropBase":-1,"dropRange":-1},{"title":"Socket Gem","name":"|lime|Recharge","strippedName":"Recharge","imageId":"socketGemImg","description":["|orange|+5 Barrier Regeneration"],"passives":[],"flavorText":[],"groupNames":["Any Armor","Upgrade"],"rarity":"Epic","enchantable":false,"gemSlots":0,"extendSlots":0,"level":-1,"dropBase":-1,"dropRange":-1},{"title":"Socket Gem","name":"|lime|Resistance IV","strippedName":"Resistance IV","imageId":"socketGemImg","description":["|orange|+5% Elemental Resist"],"passives":[],"flavorText":[],"groupNames":["Any Armor","Upgrade"],"rarity":"Epic","enchantable":false,"gemSlots":0,"extendSlots":0,"level":-1,"dropBase":-1,"dropRange":-1},{"title":"Socket Gem","name":"|lime|Lethality III","strippedName":"Lethality III","imageId":"socketGemImg","description":["|orange|+8% Critical Chance"],"passives":[],"flavorText":[],"groupNames":["Any Weapon","Upgrade"],"rarity":"Rare","enchantable":false,"gemSlots":0,"extendSlots":0,"level":-1,"dropBase":-1,"dropRange":-1},{"title":"Socket Gem","name":"|lime|Life II","strippedName":"Life II","imageId":"socketGemImg","description":["|orange|+4 Maximum Life"],"passives":[],"flavorText":[],"groupNames":["Any Armor","Upgrade"],"rarity":"Common","enchantable":false,"gemSlots":0,"extendSlots":0,"level":-1,"dropBase":-1,"dropRange":-1},{"title":"Socket Gem","name":"|lime|Aptitude","strippedName":"Aptitude","imageId":"socketGemImg","description":["|orange|+2% Combat XP"],"passives":[],"flavorText":[],"groupNames":["Any Armor","Upgrade"],"rarity":"Rare","enchantable":false,"gemSlots":0,"extendSlots":0,"level":-1,"dropBase":-1,"dropRange":-1},{"title":"Socket Gem","name":"|lime|Precise III","strippedName":"Precise III","imageId":"socketGemImg","description":["|orange|+8 Accuracy"],"passives":[],"flavorText":[],"groupNames":["Any Weapon","Upgrade"],"rarity":"Rare","enchantable":false,"gemSlots":0,"extendSlots":0,"level":-1,"dropBase":-1,"dropRange":-1},{"title":"Socket Gem","name":"|lime|Elemental Energy","strippedName":"Elemental Energy","imageId":"socketGemImg","description":["|orange|+6% Element Status Chance"],"passives":[],"flavorText":[],"groupNames":["Any Weapon","Upgrade"],"rarity":"Epic","enchantable":false,"gemSlots":0,"extendSlots":0,"level":-1,"dropBase":-1,"dropRange":-1},{"title":"Socket Gem","name":"|lime|Barrier II","strippedName":"Barrier II","imageId":"socketGemImg","description":["|orange|+4 Maximum Barrier"],"passives":[],"flavorText":[],"groupNames":["Any Armor","Upgrade"],"rarity":"Common","enchantable":false,"gemSlots":0,"extendSlots":0,"level":-1,"dropBase":-1,"dropRange":-1},{"title":"Socket Gem","name":"|lime|Ebb","strippedName":"Ebb","imageId":"socketGemImg","description":["|none|丕","|yellow|Heal |white|10% Life","|yellow|Gain |white|Speed II |cyan|30|none|峔"],"passives":[],"flavorText":[],"groupNames":["Any Armor","Upgrade"],"rarity":"Epic","specialFlag":"transmute","enchantable":false,"gemSlots":0,"extendSlots":0,"level":-1,"dropBase":-1,"dropRange":-1},{"title":"Socket Gem","name":"|lime|Chill III","strippedName":"Chill III","imageId":"socketGemImg","description":["|orange|+4 Ice Damage"],"passives":[],"flavorText":[],"groupNames":["Any Weapon","Upgrade"],"rarity":"Rare","enchantable":false,"gemSlots":0,"extendSlots":0,"level":-1,"dropBase":-1,"dropRange":-1},{"title":"Socket Gem","name":"|lime|Kinetic Absorption","strippedName":"Kinetic Absorption","imageId":"socketGemImg","description":["|none|业|red|[30% Chance]","|yellow|Gain |white|1 |green|Earth Rune"],"passives":[],"flavorText":[],"groupNames":["Any Shield","Upgrade"],"rarity":"Epic","enchantable":false,"gemSlots":0,"extendSlots":0,"level":-1,"dropBase":-1,"dropRange":-1},{"title":"Socket Gem","name":"|lime|Shine II","strippedName":"Shine II","imageId":"socketGemImg","description":["|orange|+3 Light Damage"],"passives":[],"flavorText":[],"groupNames":["Any Weapon","Upgrade"],"rarity":"Common","enchantable":false,"gemSlots":0,"extendSlots":0,"level":-1,"dropBase":-1,"dropRange":-1},{"title":"Socket Gem","name":"|lime|Subtle Healing","strippedName":"Subtle Healing","imageId":"socketGemImg","description":["|orange|+1 Life Regeneration"],"passives":[],"flavorText":[],"groupNames":["Offhand Items","Upgrade"],"rarity":"Rare","enchantable":false,"gemSlots":0,"extendSlots":0,"level":-1,"dropBase":-1,"dropRange":-1},{"title":"Socket Gem","name":"|lime|Discovery","strippedName":"Discovery","imageId":"socketGemImg","description":["|orange|+4% Loot Bonus"],"passives":[],"flavorText":[],"groupNames":["Any Weapon","Upgrade"],"rarity":"Rare","enchantable":false,"gemSlots":0,"extendSlots":0,"level":-1,"dropBase":-1,"dropRange":-1},{"title":"Socket Gem","name":"|lime|Frenzy III","strippedName":"Frenzy III","imageId":"socketGemImg","description":["|orange|+7% Attack Speed"],"passives":[],"flavorText":[],"groupNames":["Any Weapon","Upgrade"],"rarity":"Rare","enchantable":false,"gemSlots":0,"extendSlots":0,"level":-1,"dropBase":-1,"dropRange":-1},{"title":"Socket Gem","name":"|lime|Barrier IV","strippedName":"Barrier IV","imageId":"socketGemImg","description":["|orange|+8 Maximum Barrier"],"passives":[],"flavorText":[],"groupNames":["Any Armor","Upgrade"],"rarity":"Epic","enchantable":false,"gemSlots":0,"extendSlots":0,"level":-1,"dropBase":-1,"dropRange":-1},{"title":"Socket Gem","name":"|lime|Double Draw","strippedName":"Double Draw","imageId":"socketGemImg","description":["|orange|+1 Extra Projectiles"],"passives":[],"flavorText":[],"groupNames":["Quivers","Upgrade"],"rarity":"Rare","enchantable":false,"gemSlots":0,"extendSlots":0,"level":-1,"dropBase":-1,"dropRange":-1},{"title":"Socket Gem","name":"|lime|Earth Aspect","strippedName":"Earth Aspect","imageId":"socketGemImg","description":["|orange|+3 Earth Damage"],"passives":[],"flavorText":[],"groupNames":["Any Shield","Upgrade"],"rarity":"Rare","enchantable":false,"gemSlots":0,"extendSlots":0,"level":-1,"dropBase":-1,"dropRange":-1},{"title":"Socket Gem","name":"|lime|Prismatic Energy","strippedName":"Prismatic Energy","imageId":"socketGemImg","description":["|none|丗 Prismatic Aura","|yellow|Adds |white|Energize II"],"passives":[],"flavorText":[],"groupNames":["Any Armor","Upgrade"],"rarity":"Epic","enchantable":false,"gemSlots":0,"extendSlots":0,"level":-1,"dropBase":-1,"dropRange":-1},{"title":"Socket Gem","name":"|lime|Frenzy I","strippedName":"Frenzy I","imageId":"socketGemImg","description":["|orange|+5% Attack Speed"],"passives":[],"flavorText":[],"groupNames":["Any Weapon","Upgrade"],"rarity":"Common","enchantable":false,"gemSlots":0,"extendSlots":0,"level":-1,"dropBase":-1,"dropRange":-1},{"title":"Socket Gem","name":"|lime|Lethality IV","strippedName":"Lethality IV","imageId":"socketGemImg","description":["|orange|+10% Critical Chance"],"passives":[],"flavorText":[],"groupNames":["Any Weapon","Upgrade"],"rarity":"Epic","enchantable":false,"gemSlots":0,"extendSlots":0,"level":-1,"dropBase":-1,"dropRange":-1},{"title":"Socket Gem","name":"|lime|Brutality II","strippedName":"Brutality II","imageId":"socketGemImg","description":["|orange|+12% Critical Multiplier"],"passives":[],"flavorText":[],"groupNames":["Any Weapon","Upgrade"],"rarity":"Common","enchantable":false,"gemSlots":0,"extendSlots":0,"level":-1,"dropBase":-1,"dropRange":-1},{"title":"Socket Gem","name":"|lime|Sunder III","strippedName":"Sunder III","imageId":"socketGemImg","description":["|orange|+10 Armor Penetration"],"passives":[],"flavorText":[],"groupNames":["Physical Weapons","Upgrade"],"rarity":"Rare","enchantable":false,"gemSlots":0,"extendSlots":0,"level":-1,"dropBase":-1,"dropRange":-1},{"title":"Socket Gem","name":"|lime|Block I","strippedName":"Block I","imageId":"socketGemImg","description":["|orange|+6 Block"],"passives":[],"flavorText":[],"groupNames":["Any Shield","Upgrade"],"rarity":"Common","enchantable":false,"gemSlots":0,"extendSlots":0,"level":-1,"dropBase":-1,"dropRange":-1},{"title":"Socket Gem","name":"|lime|War Rhythm","strippedName":"War Rhythm","imageId":"socketGemImg","description":["|none|丐","|yellow|Reduce the cooldown of","|white||ul|Battle Energy|yellow| by |lgreen|0.5|none|峓"],"passives":[],"flavorText":[],"groupNames":["Any Weapon","Upgrade"],"rarity":"Epic","specialFlag":"transmute","enchantable":false,"gemSlots":0,"extendSlots":0,"level":-1,"dropBase":-1,"dropRange":-1},{"title":"Socket Gem","name":"|lime|Lethality II","strippedName":"Lethality II","imageId":"socketGemImg","description":["|orange|+7% Critical Chance"],"passives":[],"flavorText":[],"groupNames":["Any Weapon","Upgrade"],"rarity":"Common","enchantable":false,"gemSlots":0,"extendSlots":0,"level":-1,"dropBase":-1,"dropRange":-1},{"title":"Socket Gem","name":"|lime|Swiftness","strippedName":"Swiftness","imageId":"socketGemImg","description":["|orange|+3 Movement Speed"],"passives":[],"flavorText":[],"groupNames":["Any Boots","Upgrade"],"rarity":"Epic","enchantable":false,"gemSlots":0,"extendSlots":0,"level":-1,"dropBase":-1,"dropRange":-1},{"title":"Socket Gem","name":"|lime|Shine IV","strippedName":"Shine IV","imageId":"socketGemImg","description":["|orange|+5 Light Damage"],"passives":[],"flavorText":[],"groupNames":["Any Weapon","Upgrade"],"rarity":"Epic","enchantable":false,"gemSlots":0,"extendSlots":0,"level":-1,"dropBase":-1,"dropRange":-1},{"title":"Socket Gem","name":"|lime|Barrier III","strippedName":"Barrier III","imageId":"socketGemImg","description":["|orange|+6 Maximum Barrier"],"passives":[],"flavorText":[],"groupNames":["Any Armor","Upgrade"],"rarity":"Rare","enchantable":false,"gemSlots":0,"extendSlots":0,"level":-1,"dropBase":-1,"dropRange":-1},{"title":"Socket Gem","name":"|lime|Prismatic Rage","strippedName":"Prismatic Rage","imageId":"socketGemImg","description":["|none|丗 Prismatic Aura","|yellow|Gain |red|2|none|峐 |yellow|per second"],"passives":[],"flavorText":[],"groupNames":["Any Armor","Upgrade"],"rarity":"Epic","enchantable":false,"gemSlots":0,"extendSlots":0,"level":-1,"dropBase":-1,"dropRange":-1},{"title":"Socket Gem","name":"|lime|Hint Of Strength","strippedName":"Hint Of Strength","imageId":"socketGemImg","description":["|orange|+1 Physical Damage"],"passives":[],"flavorText":[],"groupNames":["Offhand Items","Upgrade"],"rarity":"Rare","enchantable":false,"gemSlots":0,"extendSlots":0,"level":-1,"dropBase":-1,"dropRange":-1},{"title":"Socket Gem","name":"|lime|Brutality IV","strippedName":"Brutality IV","imageId":"socketGemImg","description":["|orange|+16% Critical Multiplier"],"passives":[],"flavorText":[],"groupNames":["Any Weapon","Upgrade"],"rarity":"Epic","enchantable":false,"gemSlots":0,"extendSlots":0,"level":-1,"dropBase":-1,"dropRange":-1},{"title":"Socket Gem","name":"|lime|Touch Of Joy","strippedName":"Touch Of Joy","imageId":"socketGemImg","description":["|orange|+5% Light Damage"],"passives":[],"flavorText":[],"groupNames":["Offhand Items","Upgrade"],"rarity":"Rare","enchantable":false,"gemSlots":0,"extendSlots":0,"level":-1,"dropBase":-1,"dropRange":-1},{"title":"Socket Gem","name":"|lime|Life I","strippedName":"Life I","imageId":"socketGemImg","description":["|orange|+2 Maximum Life"],"passives":[],"flavorText":[],"groupNames":["Any Armor","Upgrade"],"rarity":"Common","enchantable":false,"gemSlots":0,"extendSlots":0,"level":-1,"dropBase":-1,"dropRange":-1},{"title":"Socket Gem","name":"|lime|Touch Of Heat","strippedName":"Touch Of Heat","imageId":"socketGemImg","description":["|orange|+5% Fire Damage"],"passives":[],"flavorText":[],"groupNames":["Offhand Items","Upgrade"],"rarity":"Rare","enchantable":false,"gemSlots":0,"extendSlots":0,"level":-1,"dropBase":-1,"dropRange":-1},{"title":"Socket Gem","name":"|lime|Surge","strippedName":"Surge","imageId":"socketGemImg","description":["|none|丗 Rush","|yellow|Gain |white|+20% Attack Speed |cyan|6|none|峔"],"passives":[],"flavorText":[],"groupNames":["Any Boots","Upgrade"],"rarity":"Epic","enchantable":false,"gemSlots":0,"extendSlots":0,"level":-1,"dropBase":-1,"dropRange":-1},{"title":"Socket Gem","name":"|lime|Zap III","strippedName":"Zap III","imageId":"socketGemImg","description":["|orange|+4 Lightning Damage"],"passives":[],"flavorText":[],"groupNames":["Any Weapon","Upgrade"],"rarity":"Rare","enchantable":false,"gemSlots":0,"extendSlots":0,"level":-1,"dropBase":-1,"dropRange":-1},{"title":"Socket Gem","name":"|lime|Impact I","strippedName":"Impact I","imageId":"socketGemImg","description":["|orange|+2 Physical Damage"],"passives":[],"flavorText":[],"groupNames":["Any Weapon","Upgrade"],"rarity":"Common","enchantable":false,"gemSlots":0,"extendSlots":0,"level":-1,"dropBase":-1,"dropRange":-1},{"title":"Socket Gem","name":"|lime|Spider Bite","strippedName":"Spider Bite","imageId":"socketGemImg","description":["|orange|+8% Poison Chance","|orange|+10% Poison Duration"],"passives":[],"flavorText":[],"groupNames":["Any Weapon","Upgrade"],"rarity":"Epic","enchantable":false,"gemSlots":0,"extendSlots":0,"level":-1,"dropBase":-1,"dropRange":-1},{"title":"Socket Gem","name":"|lime|Stonewall","strippedName":"Stonewall","imageId":"socketGemImg","description":["|orange|+6 Block","|orange|+2 Earth Damage"],"passives":[],"flavorText":[],"groupNames":["Any Shield","Upgrade"],"rarity":"Epic","specialFlag":"transmute","enchantable":false,"gemSlots":0,"extendSlots":0,"level":-1,"dropBase":-1,"dropRange":-1},{"title":"Socket Gem","name":"|lime|Overdrive","strippedName":"Overdrive","imageId":"socketGemImg","description":["|none|丗 Battle Energy","|yellow|Reduce the cooldown of |orange|yellow","|yellow|and |blue|blue |yellow|abilities by |lgreen|2|none|峓"],"passives":[],"flavorText":[],"groupNames":["Any Armor","Upgrade"],"rarity":"Epic","specialFlag":"transmute","enchantable":false,"gemSlots":0,"extendSlots":0,"level":-1,"dropBase":-1,"dropRange":-1},{"title":"Socket Gem","name":"|lime|Frog Aspect","strippedName":"Frog Aspect","imageId":"socketGemImg","description":["|none|丒","|yellow|Gain |white|Jump II"],"passives":[],"flavorText":[],"groupNames":["Any Boots","Upgrade"],"rarity":"Epic","specialFlag":"transmute","enchantable":false,"gemSlots":0,"extendSlots":0,"level":-1,"dropBase":-1,"dropRange":-1},{"title":"Socket Gem","name":"|lime|Steal","strippedName":"Steal","imageId":"socketGemImg","description":["|orange|+4% Bits Dropped"],"passives":[],"flavorText":[],"groupNames":["Any Weapon","Upgrade"],"rarity":"Rare","enchantable":false,"gemSlots":0,"extendSlots":0,"level":-1,"dropBase":-1,"dropRange":-1},{"title":"Socket Gem","name":"|lime|Lacerate I","strippedName":"Lacerate I","imageId":"socketGemImg","description":["|orange|+6% Bleed Chance"],"passives":[],"flavorText":[],"groupNames":["Physical Weapons","Upgrade"],"rarity":"Common","enchantable":false,"gemSlots":0,"extendSlots":0,"level":-1,"dropBase":-1,"dropRange":-1},{"title":"Socket Gem","name":"|lime|Joint Seeker","strippedName":"Joint Seeker","imageId":"socketGemImg","description":["|orange|+2% Critical Chance"],"passives":[],"flavorText":[],"groupNames":["Offhand Items","Upgrade"],"rarity":"Rare","enchantable":false,"gemSlots":0,"extendSlots":0,"level":-1,"dropBase":-1,"dropRange":-1},{"title":"Socket Gem","name":"|lime|Lightweight","strippedName":"Lightweight","imageId":"socketGemImg","description":["|orange|+2 Movement Speed"],"passives":[],"flavorText":[],"groupNames":["Any Armor","Upgrade"],"rarity":"Rare","enchantable":false,"gemSlots":0,"extendSlots":0,"level":-1,"dropBase":-1,"dropRange":-1},{"title":"Socket Gem","name":"|lime|Frenzy II","strippedName":"Frenzy II","imageId":"socketGemImg","description":["|orange|+6% Attack Speed"],"passives":[],"flavorText":[],"groupNames":["Any Weapon","Upgrade"],"rarity":"Common","enchantable":false,"gemSlots":0,"extendSlots":0,"level":-1,"dropBase":-1,"dropRange":-1},{"title":"Socket Gem","name":"|lime|Intimidate","strippedName":"Intimidate","imageId":"socketGemImg","description":["|none|且","|yellow|Inflict |white|Weak II |pink|22|none|峑 |cyan|20|none|峔"],"passives":[],"flavorText":[],"groupNames":["Any Armor","Upgrade"],"rarity":"Rare","enchantable":false,"gemSlots":0,"extendSlots":0,"level":-1,"dropBase":-1,"dropRange":-1},{"title":"Socket Gem","name":"|lime|Burn II","strippedName":"Burn II","imageId":"socketGemImg","description":["|orange|+3 Fire Damage"],"passives":[],"flavorText":[],"groupNames":["Any Weapon","Upgrade"],"rarity":"Common","enchantable":false,"gemSlots":0,"extendSlots":0,"level":-1,"dropBase":-1,"dropRange":-1},{"title":"Socket Gem","name":"|lime|Superior Dexterity","strippedName":"Superior Dexterity","imageId":"socketGemImg","description":["|orange|+5% Critical Chance","|orange|+8 Accuracy"],"passives":[],"flavorText":[],"groupNames":["Melee Weapons","Upgrade"],"rarity":"Epic","enchantable":false,"gemSlots":0,"extendSlots":0,"level":-1,"dropBase":-1,"dropRange":-1},{"title":"Socket Gem","name":"|lime|Pain Barrier","strippedName":"Pain Barrier","imageId":"socketGemImg","description":["|none|丘","|yellow|Restores |white|6 + 4% |yellow|barrier","|white|[2s Cooldown]"],"passives":[],"flavorText":[],"groupNames":["Any Helmet","Upgrade"],"rarity":"Epic","enchantable":false,"gemSlots":0,"extendSlots":0,"level":-1,"dropBase":-1,"dropRange":-1},{"title":"Socket Gem","name":"|lime|Bloodstains","strippedName":"Bloodstains","imageId":"socketGemImg","description":["|orange|+5% Critical Multiplier"],"passives":[],"flavorText":[],"groupNames":["Any Armor","Upgrade"],"rarity":"Rare","enchantable":false,"gemSlots":0,"extendSlots":0,"level":-1,"dropBase":-1,"dropRange":-1},{"title":"Socket Gem","name":"|lime|Frenzy IV","strippedName":"Frenzy IV","imageId":"socketGemImg","description":["|orange|+8% Attack Speed"],"passives":[],"flavorText":[],"groupNames":["Any Weapon","Upgrade"],"rarity":"Epic","enchantable":false,"gemSlots":0,"extendSlots":0,"level":-1,"dropBase":-1,"dropRange":-1},{"title":"Socket Gem","name":"|lime|Burn IV","strippedName":"Burn IV","imageId":"socketGemImg","description":["|orange|+5 Fire Damage"],"passives":[],"flavorText":[],"groupNames":["Any Weapon","Upgrade"],"rarity":"Epic","enchantable":false,"gemSlots":0,"extendSlots":0,"level":-1,"dropBase":-1,"dropRange":-1},{"title":"Socket Gem","name":"|lime|Shade III","strippedName":"Shade III","imageId":"socketGemImg","description":["|orange|+4 Shadow Damage"],"passives":[],"flavorText":[],"groupNames":["Any Weapon","Upgrade"],"rarity":"Rare","enchantable":false,"gemSlots":0,"extendSlots":0,"level":-1,"dropBase":-1,"dropRange":-1},{"title":"Socket Gem","name":"|lime|Fortune","strippedName":"Fortune","imageId":"socketGemImg","description":["|orange|+1% Loot Bonus"],"passives":[],"flavorText":[],"groupNames":["Any Armor","Upgrade"],"rarity":"Rare","enchantable":false,"gemSlots":0,"extendSlots":0,"level":-1,"dropBase":-1,"dropRange":-1},{"title":"Socket Gem","name":"|lime|Energy I","strippedName":"Energy I","imageId":"socketGemImg","description":["|orange|+10 Maximum Energy"],"passives":[],"flavorText":[],"groupNames":["Any Armor","Upgrade"],"rarity":"Common","enchantable":false,"gemSlots":0,"extendSlots":0,"level":-1,"dropBase":-1,"dropRange":-1},{"title":"Socket Gem","name":"|lime|Concentration","strippedName":"Concentration","imageId":"socketGemImg","description":["|none|东","|yellow|Restores |white|5 Barrier"],"passives":[],"flavorText":[],"groupNames":["Magical Weapons","Upgrade"],"rarity":"Epic","specialFlag":"transmute","enchantable":false,"gemSlots":0,"extendSlots":0,"level":-1,"dropBase":-1,"dropRange":-1},{"title":"Socket Gem","name":"|lime|Heroic Heart","strippedName":"Heroic Heart","imageId":"socketGemImg","description":["|orange|+10 Block","|orange|+2 Maximum Life"],"passives":[],"flavorText":[],"groupNames":["Any Shield","Upgrade"],"rarity":"Epic","enchantable":false,"gemSlots":0,"extendSlots":0,"level":-1,"dropBase":-1,"dropRange":-1},{"title":"Socket Gem","name":"|lime|Two In The Chamber","strippedName":"Two In The Chamber","imageId":"socketGemImg","description":["|orange|+1 Extra Projectiles"],"passives":[],"flavorText":[],"groupNames":["Ammunition","Upgrade"],"rarity":"Rare","enchantable":false,"gemSlots":0,"extendSlots":0,"level":-1,"dropBase":-1,"dropRange":-1},{"title":"Socket Gem","name":"|lime|Mercy","strippedName":"Mercy","imageId":"socketGemImg","description":["|none|丐"," |red|[REQ: Target Below 10% Life]","|yellow|Instantly kill target"],"passives":[],"flavorText":[],"groupNames":["Any Weapon","Upgrade"],"rarity":"Rare","enchantable":false,"gemSlots":0,"extendSlots":0,"level":-1,"dropBase":-1,"dropRange":-1}]